st_image_carousel/__init__.py
st_image_carousel/frontend/build/index.html
st_image_carousel/frontend/build/index.mjs
st_image_carousel-0.1.4.dist-info/licenses/LICENSE
st_image_carousel-0.1.4.dist-info/METADATA
st_image_carousel-0.1.4.dist-info/WHEEL
st_image_carousel-0.1.4.dist-info/top_level.txt
st_image_carousel-0.1.4.dist-info/RECORD
